README.md
setup.py
lbrlabs_pulumiservice/__init__.py
lbrlabs_pulumiservice/_utilities.py
lbrlabs_pulumiservice/cert_thumb_print.py
lbrlabs_pulumiservice/provider.py
lbrlabs_pulumiservice/pulumi-plugin.json
lbrlabs_pulumiservice/py.typed
lbrlabs_pulumiservice.egg-info/PKG-INFO
lbrlabs_pulumiservice.egg-info/SOURCES.txt
lbrlabs_pulumiservice.egg-info/dependency_links.txt
lbrlabs_pulumiservice.egg-info/not-zip-safe
lbrlabs_pulumiservice.egg-info/requires.txt
lbrlabs_pulumiservice.egg-info/top_level.txt