Metadata-Version: 2.1
Name: lbrlabs-pulumiservice
Version: 0.0.1a1680369404
Summary: A Pulumi provider for retrieving the thumbprint of a remote certificate
Home-page: https://lbrlabs.com
License: Apache-2.0
Project-URL: Repository, https://github.com/lbrlabs/pulumi-remotecertificate/
Keywords: pulumi provider remote certificate thumbprint
Requires-Python: >=3.7
